yaml_header_tools/__init__.py
yaml_header_tools/yaml_header_tools.py
yaml_header_tools-0.2.1.dist-info/LICENSE
yaml_header_tools-0.2.1.dist-info/METADATA
yaml_header_tools-0.2.1.dist-info/WHEEL
yaml_header_tools-0.2.1.dist-info/top_level.txt
yaml_header_tools-0.2.1.dist-info/RECORD
