Metadata-Version: 2.1
Name: yaml-header-tools
Version: 0.2.1
Summary: Tools for reading yaml headers from markdown files
Author: Alexander Schlemmer
Author-email: alexander@mail-schlemmer.de
Classifier: Programming Language :: Python :: 3
Classifier: License :: OSI Approved :: GNU Affero General Public License v3
Classifier: Operating System :: OS Independent
Requires-Python: >=3.6
License-File: LICENSE
